MANIFEST.in
README.md
setup.py
easy_memmap/__init__.py
easy_memmap/easy_mapper.py
easy_memmap.egg-info/PKG-INFO
easy_memmap.egg-info/SOURCES.txt
easy_memmap.egg-info/dependency_links.txt
easy_memmap.egg-info/requires.txt
easy_memmap.egg-info/top_level.txt