Metadata-Version: 2.1
Name: easy-memmap
Version: 0.0.2
Summary: Easy memmap
Home-page: https://github.com/charlielito/easy_memmap
Author: Carlos Alvarez
Author-email: candres.alv@gmail.com
License: MIT
Platform: UNKNOWN
